APIFixer/APIFixer.py
APIFixer/__init__.py
APIFixer-1.1.1.dist-info/LICENSE
APIFixer-1.1.1.dist-info/METADATA
APIFixer-1.1.1.dist-info/WHEEL
APIFixer-1.1.1.dist-info/top_level.txt
APIFixer-1.1.1.dist-info/RECORD
