Metadata-Version: 2.1
Name: APIFixer
Version: 1.1.1
Summary: APIFixer is a Python class that automatically starts an API server, checks its routes, generates documentation based on the OpenAI API, and tests API endpoints to fix bugs and improve API performance.
Home-page: https://github.com/gods-created/APIFixer
Author: Bohdan Terskow
Author-email: bohdanterskow@gmail.com
Keywords: python,logs,api,fastapi,docs,ai,openai
Classifier: Development Status :: 1 - Planning
Classifier: Intended Audience :: Developers
Classifier: Programming Language :: Python :: 3
Classifier: Operating System :: Unix
Classifier: Operating System :: MacOS :: MacOS X
Classifier: Operating System :: Microsoft :: Windows
License-File: LICENSE
Requires-Dist: loguru
Requires-Dist: openai
Requires-Dist: requests
Requires-Dist: uvicorn
